Workbook
Name Slicer_Assigned_Team: #N/A
Name Slicer_MONTH: #N/A
Name Slicer_Priority: #N/A
Name Slicer_State: #N/A

Sheet servicenow data
A1: Problem Ticket | B1: Problem Statement | C1: Description | D1: Cause | E1: State | F1: Priority | G1: Assigned Team | H1: Date | I1: Age (Days) | J1: YEAR | K1: MONTH | L1: DAYNAME | M1: DAY | N1: WEEKNUM | O1: WEEKDAY | P1: QUARTER | Q1: MONTH SATRT | R1: MONTH END | S1: YEAR_START | T1: YEAR_END | U1: QUARTER_START | V1: QUARTER_END | W1: WEEK_START | X1: WEEK_END | Y1: Status Group | Z1: Age Bucket
A2: PRB1001860 | B2: Virtualization Platform reporting relationship errors | C2: Infrastructure monitoring identified data completeness in virtualization platform. Relationship errors discovered during validation. This issue is caused by a network configuration error. When a remote machine is running on a VPN service, it can connect to the same VPN service using the same IP address. Immediate remediation required. | D2: Virtualization Platform configuration lacking data completeness enforcement | E2: In Progress | F2: High | G2: Backup & Recovery | H2: 45926 | I2: 32 | J2: =YEAR(H:H) -> 2025 | K2: =MONTH(H:H) -> 9 | L2: =TEXT(H2,"DDD") -> Fri | M2: =DAY(H:H) -> 26 | N2: =WEEKNUM(H2,1) -> 39 | O2: =WEEKDAY(H2,1) -> 6 | P2: =IF(MONTH(H2)<3,"Q1",IF(MONTH(H2)<6,"Q2",IF(MONTH(H2)<9,"Q3","Q4"))) -> Q4 | Q2: =EOMONTH(H2,-1)+1 -> 45901 | R2: =EOMONTH(H2,0) -> 45930 | S2: =DATE(YEAR(H2),1,1) -> 45658 | T2: =DATE(YEAR(H2),12,31) -> 46022 | U2: =DATE(YEAR(H2),IF(MONTH(H2)<=3,1,IF(MONTH(H2)<=6,4,IF(MONTH(H2)<=9,7,10))),1) -> 45839 | V2: =EOMONTH(DATE(YEAR(H2),IF(MONTH(H2)<=3,3,IF(MONTH(H2)<=6,6,IF(MONTH(H2)<=9,9,12))),1),0) -> 45930 | W2: =H2-WEEKDAY(H2,1)+1 -> 45921 | X2: =H2+7-WEEKDAY(H2,1) -> 45927 | Y2: =IF(OR(E2="Closed",E2="Resolved"),"Completed","Active") -> Active | Z2: =IF(I2="","",IF(I2<=15,"0-15",IF(I2<=30,"16-30",IF(I2<=60,"31-60",IF(I2<=90,"61-90","90+"))))) -> 31-60
A3: PRB1000353 | B3: Patch Management experiencing connectivity issues | C3: Monitoring detected connectivity issues in patch management. Affected server: 1. 0. | D3: Resource allocation for patch management requires optimization | E3: In Progress | F3: High | G3: Backup & Recovery | H3: 45926 | I3: 32 | J3: =YEAR(H:H) -> 2025 | K3: =MONTH(H:H) -> 9 | L3: =TEXT(H3,"DDD") -> Fri | M3: =DAY(H:H) -> 26 | N3: =WEEKNUM(H3,1) -> 39 | O3: =WEEKDAY(H3,1) -> 6 | P3: =IF(MONTH(H3)<3,"Q1",IF(MONTH(H3)<6,"Q2",IF(MONTH(H3)<9,"Q3","Q4"))) -> Q4 | Q3: =EOMONTH(H3,-1)+1 -> 45901 | R3: =EOMONTH(H3,0) -> 45930 | S3: =EOMONTH(H2,-MONTH(H2))+1 -> 45658 | T3: =EOMONTH(H2,12-MONTH(H2)) -> 46022 | U3: =DATE(YEAR(H3),IF(MONTH(H3)<=3,1,IF(MONTH(H3)<=6,4,IF(MONTH(H3)<=9,7,10))),1) -> 45839 | V3: =EOMONTH(DATE(YEAR(H3),IF(MONTH(H3)<=3,3,IF(MONTH(H3)<=6,6,IF(MONTH(H3)<=9,9,12))),1),0) -> 45930 | W3: =H3-WEEKDAY(H3,1)+1 -> 45921 | X3: =H3+7-WEEKDAY(H3,1) -> 45927 | Y3: =IF(OR(E3="Closed",E3="Resolved"),"Completed","Active") -> Active | Z3: =IF(I3="","",IF(I3<=15,"0-15",IF(I3<=30,"16-30",IF(I3<=60,"31-60",IF(I3<=90,"61-90","90+"))))) -> 31-60
A4: PRB1001333 | B4: Application Gateway experiencing performance degradation | C4: Monitoring detected performance degradation in application gateway. Credential Management Dependencies Credential management is a process that takes a user's credentials into account, and enables them to manage their own settings. For example, you can configure the security key of your device to provide a password on each login and reset password of a trusted service. | D4: Resource allocation for application gateway requires optimization | E4: Open | F4: High | G4: CMDB Team | H4: 45941 | I4: 17 | J4: =YEAR(H:H) -> 2025 | K4: =MONTH(H:H) -> 10 | L4: =TEXT(H4,"DDD") -> Sat | M4: =DAY(H:H) -> 11 | N4: =WEEKNUM(H4,1) -> 41 | O4: =WEEKDAY(H4,1) -> 7 | P4: =IF(MONTH(H4)<3,"Q1",IF(MONTH(H4)<6,"Q2",IF(MONTH(H4)<9,"Q3","Q4"))) -> Q4 | Q4: =EOMONTH(H4,-1)+1 -> 45931 | R4: =EOMONTH(H4,0) -> 45961 | S4: =EOMONTH(H3,-MONTH(H3))+1 -> 45658 | T4: =EOMONTH(H3,12-MONTH(H3)) -> 46022 | U4: =DATE(YEAR(H4),IF(MONTH(H4)<=3,1,IF(MONTH(H4)<=6,4,IF(MONTH(H4)<=9,7,10))),1) -> 45931 | V4: =EOMONTH(DATE(YEAR(H4),IF(MONTH(H4)<=3,3,IF(MONTH(H4)<=6,6,IF(MONTH(H4)<=9,9,12))),1),0) -> 46022 | W4: =H4-WEEKDAY(H4,1)+1 -> 45935 | X4: =H4+7-WEEKDAY(H4,1) -> 45941 | Y4: =IF(OR(E4="Closed",E4="Resolved"),"Completed","Active") -> Active | Z4: =IF(I4="","",IF(I4<=15,"0-15",IF(I4<=30,"16-30",IF(I4<=60,"31-60",IF(I4<=90,"61-90","90+"))))) -> 16-30
A5: PRB1000905 | B5: Backup Verification experiencing resource constraints | C5: Monitoring detected resource constraints in backup verification. This bug was reported to be present in the AUR. CVE-2017-8332 A vulnerability in the Microsoft Windows Virtual Machine (VM) driver in Microsoft Windows 8. | D5: Resource allocation for backup verification requires optimization | E5: Awaiting Info | F5: High | G5: Infrastructure | H5: 45882 | I5: 76 | J5: =YEAR(H:H) -> 2025 | K5: =MONTH(H:H) -> 8 | L5: =TEXT(H5,"DDD") -> Wed | M5: =DAY(H:H) -> 13 | N5: =WEEKNUM(H5,1) -> 33 | O5: =WEEKDAY(H5,1) -> 4 | P5: =IF(MONTH(H5)<3,"Q1",IF(MONTH(H5)<6,"Q2",IF(MONTH(H5)<9,"Q3","Q4"))) -> Q3 | Q5: =EOMONTH(H5,-1)+1 -> 45870 | R5: =EOMONTH(H5,0) -> 45900 | S5: =EOMONTH(H4,-MONTH(H4))+1 -> 45658 | T5: =EOMONTH(H4,12-MONTH(H4)) -> 46022 | U5: =DATE(YEAR(H5),IF(MONTH(H5)<=3,1,IF(MONTH(H5)<=6,4,IF(MONTH(H5)<=9,7,10))),1) -> 45839 | V5: =EOMONTH(DATE(YEAR(H5),IF(MONTH(H5)<=3,3,IF(MONTH(H5)<=6,6,IF(MONTH(H5)<=9,9,12))),1),0) -> 45930 | W5: =H5-WEEKDAY(H5,1)+1 -> 45879 | X5: =H5+7-WEEKDAY(H5,1) -> 45885 | Y5: =IF(OR(E5="Closed",E5="Resolved"),"Completed","Active") -> Active | Z5: =IF(I5="","",IF(I5<=15,"0-15",IF(I5<=30,"16-30",IF(I5<=60,"31-60",IF(I5<=90,"61-90","90+"))))) -> 61-90
A6: PRB1001289 | B6: Configuration Management reporting synchronization failures | C6: Infrastructure monitoring identified incorrect data in configuration management. Synchronization failures discovered during validation. Cisco This is a problem that affects all Cisco products, including Cisco's routers, devices and other embedded components. Cisco will implement a fix and provide an update as soon as possible. Immediate remediation required. | D6: Configuration Management configuration lacking incorrect data enforcement | E6: In Progress | F6: High | G6: Database Operations | H6: 45924 | I6: 34 | J6: =YEAR(H:H) -> 2025 | K6: =MONTH(H:H) -> 9 | L6: =TEXT(H6,"DDD") -> Wed | M6: =DAY(H:H) -> 24 | N6: =WEEKNUM(H6,1) -> 39 | O6: =WEEKDAY(H6,1) -> 4 | P6: =IF(MONTH(H6)<3,"Q1",IF(MONTH(H6)<6,"Q2",IF(MONTH(H6)<9,"Q3","Q4"))) -> Q4 | Q6: =EOMONTH(H6,-1)+1 -> 45901 | R6: =EOMONTH(H6,0) -> 45930 | S6: =EOMONTH(H5,-MONTH(H5))+1 -> 45658 | T6: =EOMONTH(H5,12-MONTH(H5)) -> 46022 | U6: =DATE(YEAR(H6),IF(MONTH(H6)<=3,1,IF(MONTH(H6)<=6,4,IF(MONTH(H6)<=9,7,10))),1) -> 45839 | V6: =EOMONTH(DATE(YEAR(H6),IF(MONTH(H6)<=3,3,IF(MONTH(H6)<=6,6,IF(MONTH(H6)<=9,9,12))),1),0) -> 45930 | W6: =H6-WEEKDAY(H6,1)+1 -> 45921 | X6: =H6+7-WEEKDAY(H6,1) -> 45927 | Y6: =IF(OR(E6="Closed",E6="Resolved"),"Completed","Active") -> Active | Z6: =IF(I6="","",IF(I6<=15,"0-15",IF(I6<=30,"16-30",IF(I6<=60,"31-60",IF(I6<=90,"61-90","90+"))))) -> 31-60
A7: PRB1001273 | B7: Configuration Management experiencing connectivity issues | C7: Monitoring detected connectivity issues in configuration management. [11:45:23]EMOTE: *no key*/(monkey (912)) : <b>The monkey (912)</b> jumps! [11:45:25]EMOTE: *no key*/(monkey (912)) : <b>The monkey (912)</b> waves his tail. [11:45:26]EMOTE: *no key*/(monkey (9. | D7: Resource allocation for configuration management requires optimization | E7: Open | F7: Medium | G7: Server Management | H7: 45909 | I7: 49 | J7: =YEAR(H:H) -> 2025 | K7: =MONTH(H:H) -> 9 | L7: =TEXT(H7,"DDD") -> Tue | M7: =DAY(H:H) -> 9 | N7: =WEEKNUM(H7,1) -> 37 | O7: =WEEKDAY(H7,1) -> 3 | P7: =IF(MONTH(H7)<3,"Q1",IF(MONTH(H7)<6,"Q2",IF(MONTH(H7)<9,"Q3","Q4"))) -> Q4 | Q7: =EOMONTH(H7,-1)+1 -> 45901 | R7: =EOMONTH(H7,0) -> 45930 | S7: =EOMONTH(H6,-MONTH(H6))+1 -> 45658 | T7: =EOMONTH(H6,12-MONTH(H6)) -> 46022 | U7: =DATE(YEAR(H7),IF(MONTH(H7)<=3,1,IF(MONTH(H7)<=6,4,IF(MONTH(H7)<=9,7,10))),1) -> 45839 | V7: =EOMONTH(DATE(YEAR(H7),IF(MONTH(H7)<=3,3,IF(MONTH(H7)<=6,6,IF(MONTH(H7)<=9,9,12))),1),0) -> 45930 | W7: =H7-WEEKDAY(H7,1)+1 -> 45907 | X7: =H7+7-WEEKDAY(H7,1) -> 45913 | Y7: =IF(OR(E7="Closed",E7="Resolved"),"Completed","Active") -> Active | Z7: =IF(I7="","",IF(I7<=15,"0-15",IF(I7<=30,"16-30",IF(I7<=60,"31-60",IF(I7<=90,"61-90","90+"))))) -> 31-60
A8: PRB1000938 | B8: Disaster Recovery experiencing resource constraints | C8: Monitoring detected resource constraints in disaster recovery. There was no update for this story. Update, 6:40 p. | D8: Resource allocation for disaster recovery requires optimization | E8: Awaiting Info | F8: Medium | G8: Server Management | H8: 45891 | I8: 67 | J8: =YEAR(H:H) -> 2025 | K8: =MONTH(H:H) -> 8 | L8: =TEXT(H8,"DDD") -> Fri | M8: =DAY(H:H) -> 22 | N8: =WEEKNUM(H8,1) -> 34 | O8: =WEEKDAY(H8,1) -> 6 | P8: =IF(MONTH(H8)<3,"Q1",IF(MONTH(H8)<6,"Q2",IF(MONTH(H8)<9,"Q3","Q4"))) -> Q3 | Q8: =EOMONTH(H8,-1)+1 -> 45870 | R8: =EOMONTH(H8,0) -> 45900 | S8: =EOMONTH(H7,-MONTH(H7))+1 -> 45658 | T8: =EOMONTH(H7,12-MONTH(H7)) -> 46022 | U8: =DATE(YEAR(H8),IF(MONTH(H8)<=3,1,IF(MONTH(H8)<=6,4,IF(MONTH(H8)<=9,7,10))),1) -> 45839 | V8: =EOMONTH(DATE(YEAR(H8),IF(MONTH(H8)<=3,3,IF(MONTH(H8)<=6,6,IF(MONTH(H8)<=9,9,12))),1),0) -> 45930 | W8: =H8-WEEKDAY(H8,1)+1 -> 45886 | X8: =H8+7-WEEKDAY(H8,1) -> 45892 | Y8: =IF(OR(E8="Closed",E8="Resolved"),"Completed","Active") -> Active | Z8: =IF(I8="","",IF(I8<=15,"0-15",IF(I8<=30,"16-30",IF(I8<=60,"31-60",IF(I8<=90,"61-90","90+"))))) -> 61-90
A9: PRB1001731 | B9: Patch Management experiencing resource constraints | C9: Monitoring detected resource constraints in patch management. Update: Team investigating. Update #2: It appears that the issue has been resolved. | D9: Resource allocation for patch management requires optimization | E9: Awaiting Info | F9: Medium | G9: CMDB Team | H9: 45919 | I9: 39 | J9: =YEAR(H:H) -> 2025 | K9: =MONTH(H:H) -> 9 | L9: =TEXT(H9,"DDD") -> Fri | M9: =DAY(H:H) -> 19 | N9: =WEEKNUM(H9,1) -> 38 | O9: =WEEKDAY(H9,1) -> 6 | P9: =IF(MONTH(H9)<3,"Q1",IF(MONTH(H9)<6,"Q2",IF(MONTH(H9)<9,"Q3","Q4"))) -> Q4 | Q9: =EOMONTH(H9,-1)+1 -> 45901 | R9: =EOMONTH(H9,0) -> 45930 | S9: =EOMONTH(H8,-MONTH(H8))+1 -> 45658 | T9: =EOMONTH(H8,12-MONTH(H8)) -> 46022 | U9: =DATE(YEAR(H9),IF(MONTH(H9)<=3,1,IF(MONTH(H9)<=6,4,IF(MONTH(H9)<=9,7,10))),1) -> 45839 | V9: =EOMONTH(DATE(YEAR(H9),IF(MONTH(H9)<=3,3,IF(MONTH(H9)<=6,6,IF(MONTH(H9)<=9,9,12))),1),0) -> 45930 | W9: =H9-WEEKDAY(H9,1)+1 -> 45914 | X9: =H9+7-WEEKDAY(H9,1) -> 45920 | Y9: =IF(OR(E9="Closed",E9="Resolved"),"Completed","Active") -> Active | Z9: =IF(I9="","",IF(I9<=15,"0-15",IF(I9<=30,"16-30",IF(I9<=60,"31-60",IF(I9<=90,"61-90","90+"))))) -> 31-60
A10: PRB1000065 | B10: Web Proxy experiencing resource constraints | C10: Monitoring detected resource constraints in web proxy. "It's a problem that we have to work through," said Andrew, who is also a senior analyst at Kaspersky Lab. "The only way to address this is to have the system upgrade every time the service is down and update it every time it goes down. | D10: Resource allocation for web proxy requires optimization | E10: In Progress | F10: Medium | G10: Server Management | H10: 45938 | I10: 20 | J10: =YEAR(H:H) -> 2025 | K10: =MONTH(H:H) -> 10 | L10: =TEXT(H10,"DDD") -> Wed | M10: =DAY(H:H) -> 8 | N10: =WEEKNUM(H10,1) -> 41 | O10: =WEEKDAY(H10,1) -> 4 | P10: =IF(MONTH(H10)<3,"Q1",IF(MONTH(H10)<6,"Q2",IF(MONTH(H10)<9,"Q3","Q4"))) -> Q4 | Q10: =EOMONTH(H10,-1)+1 -> 45931 | R10: =EOMONTH(H10,0) -> 45961 | S10: =EOMONTH(H9,-MONTH(H9))+1 -> 45658 | T10: =EOMONTH(H9,12-MONTH(H9)) -> 46022 | U10: =DATE(YEAR(H10),IF(MONTH(H10)<=3,1,IF(MONTH(H10)<=6,4,IF(MONTH(H10)<=9,7,10))),1) -> 45931 | V10: =EOMONTH(DATE(YEAR(H10),IF(MONTH(H10)<=3,3,IF(MONTH(H10)<=6,6,IF(MONTH(H10)<=9,9,12))),1),0) -> 46022 | W10: =H10-WEEKDAY(H10,1)+1 -> 45935 | X10: =H10+7-WEEKDAY(H10,1) -> 45941 | Y10: =IF(OR(E10="Closed",E10="Resolved"),"Completed","Active") -> Active | Z10: =IF(I10="","",IF(I10<=15,"0-15",IF(I10<=30,"16-30",IF(I10<=60,"31-60",IF(I10<=90,"61-90","90+"))))) -> 16-30
A11: PRB1001323 | B11: Disaster Recovery reporting duplicate records | C11: Infrastructure monitoring identified inadequate data in disaster recovery. Duplicate records discovered during validation. Scheduled downtime On March 17, 2015, the AWS S3. 5-6 release was released. Immediate remediation required. | D11: Disaster Recovery configuration lacking inadequate data enforcement | E11: Closed | F11: Medium | G11: Database Operations | H11: 45921 | I11: 37 | J11: =YEAR(H:H) -> 2025 | K11: =MONTH(H:H) -> 9 | L11: =TEXT(H11,"DDD") -> Sun | M11: =DAY(H:H) -> 21 | N11: =WEEKNUM(H11,1) -> 39 | O11: =WEEKDAY(H11,1) -> 1 | P11: =IF(MONTH(H11)<3,"Q1",IF(MONTH(H11)<6,"Q2",IF(MONTH(H11)<9,"Q3","Q4"))) -> Q4 | Q11: =EOMONTH(H11,-1)+1 -> 45901 | R11: =EOMONTH(H11,0) -> 45930 | S11: =EOMONTH(H10,-MONTH(H10))+1 -> 45658 | T11: =EOMONTH(H10,12-MONTH(H10)) -> 46022 | U11: =DATE(YEAR(H11),IF(MONTH(H11)<=3,1,IF(MONTH(H11)<=6,4,IF(MONTH(H11)<=9,7,10))),1) -> 45839 | V11: =EOMONTH(DATE(YEAR(H11),IF(MONTH(H11)<=3,3,IF(MONTH(H11)<=6,6,IF(MONTH(H11)<=9,9,12))),1),0) -> 45930 | W11: =H11-WEEKDAY(H11,1)+1 -> 45921 | X11: =H11+7-WEEKDAY(H11,1) -> 45927 | Y11: =IF(OR(E11="Closed",E11="Resolved"),"Completed","Active") -> Completed | Z11: =IF(I11="","",IF(I11<=15,"0-15",IF(I11<=30,"16-30",IF(I11<=60,"31-60",IF(I11<=90,"61-90","90+"))))) -> 31-60
A12: PRB1000056 | B12: Vmware Vcenter experiencing connectivity issues | C12: Monitoring detected connectivity issues in VMware vCenter. Analysis of SQL Server logs shows that the SQL Server logs that are generated for Windows 10 are incomplete. This means that the SQL Server logs generated for Windows 10 are incomplete because they are not running the correct SQL Server workloads, such as SQL Server 2008 and SQL Server 2012. | D12: Resource allocation for VMware vCenter requires optimization | E12: Closed | F12: High | G12: Backup & Recovery | H12: 45884 | I12: 74 | J12: =YEAR(H:H) -> 2025 | K12: =MONTH(H:H) -> 8 | L12: =TEXT(H12,"DDD") -> Fri | M12: =DAY(H:H) -> 15 | N12: =WEEKNUM(H12,1) -> 33 | O12: =WEEKDAY(H12,1) -> 6 | P12: =IF(MONTH(H12)<3,"Q1",IF(MONTH(H12)<6,"Q2",IF(MONTH(H12)<9,"Q3","Q4"))) -> Q3 | Q12: =EOMONTH(H12,-1)+1 -> 45870 | R12: =EOMONTH(H12,0) -> 45900 | S12: =EOMONTH(H11,-MONTH(H11))+1 -> 45658 | T12: =EOMONTH(H11,12-MONTH(H11)) -> 46022 | U12: =DATE(YEAR(H12),IF(MONTH(H12)<=3,1,IF(MONTH(H12)<=6,4,IF(MONTH(H12)<=9,7,10))),1) -> 45839 | V12: =EOMONTH(DATE(YEAR(H12),IF(MONTH(H12)<=3,3,IF(MONTH(H12)<=6,6,IF(MONTH(H12)<=9,9,12))),1),0) -> 45930 | W12: =H12-WEEKDAY(H12,1)+1 -> 45879 | X12: =H12+7-WEEKDAY(H12,1) -> 45885 | Y12: =IF(OR(E12="Closed",E12="Resolved"),"Completed","Active") -> Completed | Z12: =IF(I12="","",IF(I12<=15,"0-15",IF(I12<=30,"16-30",IF(I12<=60,"31-60",IF(I12<=90,"61-90","90+"))))) -> 61-90
A13: PRB1001292 | B13: Configuration Management experiencing connectivity issues | C13: Monitoring detected connectivity issues in configuration management. The server has been disabled for two minutes. You can download the latest version of Java 7 or 8 from the Java SE Store. | D13: Resource allocation for configuration management requires optimization | E13: Awaiting Info | F13: High | G13: Server Management | H13: 45869 | I13: 89 | J13: =YEAR(H:H) -> 2025 | K13: =MONTH(H:H) -> 7 | L13: =TEXT(H13,"DDD") -> Thu | M13: =DAY(H:H) -> 31 | N13: =WEEKNUM(H13,1) -> 31 | O13: =WEEKDAY(H13,1) -> 5 | P13: =IF(MONTH(H13)<3,"Q1",IF(MONTH(H13)<6,"Q2",IF(MONTH(H13)<9,"Q3","Q4"))) -> Q3 | Q13: =EOMONTH(H13,-1)+1 -> 45839 | R13: =EOMONTH(H13,0) -> 45869 | S13: =EOMONTH(H12,-MONTH(H12))+1 -> 45658 | T13: =EOMONTH(H12,12-MONTH(H12)) -> 46022 | U13: =DATE(YEAR(H13),IF(MONTH(H13)<=3,1,IF(MONTH(H13)<=6,4,IF(MONTH(H13)<=9,7,10))),1) -> 45839 | V13: =EOMONTH(DATE(YEAR(H13),IF(MONTH(H13)<=3,3,IF(MONTH(H13)<=6,6,IF(MONTH(H13)<=9,9,12))),1),0) -> 45930 | W13: =H13-WEEKDAY(H13,1)+1 -> 45865 | X13: =H13+7-WEEKDAY(H13,1) -> 45871 | Y13: =IF(OR(E13="Closed",E13="Resolved"),"Completed","Active") -> Active | Z13: =IF(I13="","",IF(I13<=15,"0-15",IF(I13<=30,"16-30",IF(I13<=60,"31-60",IF(I13<=90,"61-90","90+"))))) -> 61-90
A14: PRB1001118 | B14: Patch Management experiencing resource constraints | C14: Monitoring detected resource constraints in patch management. We've had an issue with the application gateway. The gateway that we are experiencing the issue with is on the user's computer. | D14: Resource allocation for patch management requires optimization | E14: Resolved | F14: Low | G14: Infrastructure | H14: 45904 | I14: 54 | J14: =YEAR(H:H) -> 2025 | K14: =MONTH(H:H) -> 9 | L14: =TEXT(H14,"DDD") -> Thu | M14: =DAY(H:H) -> 4 | N14: =WEEKNUM(H14,1) -> 36 | O14: =WEEKDAY(H14,1) -> 5 | P14: =IF(MONTH(H14)<3,"Q1",IF(MONTH(H14)<6,"Q2",IF(MONTH(H14)<9,"Q3","Q4"))) -> Q4 | Q14: =EOMONTH(H14,-1)+1 -> 45901 | R14: =EOMONTH(H14,0) -> 45930 | S14: =EOMONTH(H13,-MONTH(H13))+1 -> 45658 | T14: =EOMONTH(H13,12-MONTH(H13)) -> 46022 | U14: =DATE(YEAR(H14),IF(MONTH(H14)<=3,1,IF(MONTH(H14)<=6,4,IF(MONTH(H14)<=9,7,10))),1) -> 45839 | V14: =EOMONTH(DATE(YEAR(H14),IF(MONTH(H14)<=3,3,IF(MONTH(H14)<=6,6,IF(MONTH(H14)<=9,9,12))),1),0) -> 45930 | W14: =H14-WEEKDAY(H14,1)+1 -> 45900 | X14: =H14+7-WEEKDAY(H14,1) -> 45906 | Y14: =IF(OR(E14="Closed",E14="Resolved"),"Completed","Active") -> Completed | Z14: =IF(I14="","",IF(I14<=15,"0-15",IF(I14<=30,"16-30",IF(I14<=60,"31-60",IF(I14<=90,"61-90","90+"))))) -> 31-60
... A2001: PRB1001126 | B2001: Patch Management reporting duplicate records | C2001: Infrastructure monitoring identified data integrity in patch management. Duplicate records discovered during validation. This is the same data that was used to determine whether the user did not have an active DNS server. Analyses are performed by the D-backup service. Immediate remediation required. | D2001: Patch Management configuration lacking data integrity enforcement | E2001: Awaiting Info | F2001: High | G2001: Backup & Recovery | H2001: 45910 | I2001: 48 | J2001: =YEAR(H:H) -> 2025 | K2001: =MONTH(H:H) -> 9 | L2001: =TEXT(H2001,"DDD") -> Wed | M2001: =DAY(H:H) -> 10 | N2001: =WEEKNUM(H2001,1) -> 37 | O2001: =WEEKDAY(H2001,1) -> 4 | P2001: =IF(MONTH(H2001)<3,"Q1",IF(MONTH(H2001)<6,"Q2",IF(MONTH(H2001)<9,"Q3","Q4"))) -> Q4 | Q2001: =EOMONTH(H2001,-1)+1 -> 45901 | R2001: =EOMONTH(H2001,0) -> 45930 | S2001: =EOMONTH(H2000,-MONTH(H2000))+1 -> 45658 | T2001: =EOMONTH(H2000,12-MONTH(H2000)) -> 46022 | U2001: =DATE(YEAR(H2001),IF(MONTH(H2001)<=3,1,IF(MONTH(H2001)<=6,4,IF(MONTH(H2001)<=9,7,10))),1) -> 45839 | V2001: =EOMONTH(DATE(YEAR(H2001),IF(MONTH(H2001)<=3,3,IF(MONTH(H2001)<=6,6,IF(MONTH(H2001)<=9,9,12))),1),0) -> 45930 | W2001: =H2001-WEEKDAY(H2001,1)+1 -> 45907 | X2001: =H2001+7-WEEKDAY(H2001,1) -> 45913 | Y2001: =IF(OR(E2001="Closed",E2001="Resolved"),"Completed","Active") -> Active | Z2001: =IF(I2001="","",IF(I2001<=15,"0-15",IF(I2001<=30,"16-30",IF(I2001<=60,"31-60",IF(I2001<=90,"61-90","90+"))))) -> 31-60

Sheet pivot table1
A2: State wise Tickets | E2: Priority wise Tickets | K2: Month wise Tickets
A3: Row Labels | B3: Count of Problem Ticket | E3: Row Labels | F3: Count of Problem Ticket | K3: Row Labels | L3: Count of Problem Ticket
A4: Awaiting Info | B4: 311 | E4: Critical | F4: 301 | K4: 7 | L4: 49
A5: Closed | B5: 200 | E5: High | F5: 496 | K5: 8 | L5: 675
A6: In Progress | B6: 554 | E6: Low | F6: 396 | K6: 9 | L6: 656
A7: Open | B7: 534 | E7: Medium | F7: 807 | K7: 10 | L7: 620
A8: Resolved | B8: 401 | E8: Grand Total | F8: 2000 | K8: Grand Total | L8: 2000
A9: Grand Total | B9: 2000
E14: Cause wise Tickets
E15: Row Labels | F15: Count of Problem Ticket | K15: Age Bucket wise Tickets
E16: Resource allocation for web proxy requires optimization | F16: 78 | K16: Row Labels | L16: Count of Problem Ticket
E17: Resource allocation for network monitoring requires optimization | F17: 75 | K17: 0-15 | L17: 328
A18: Active vs completed | E18: Resource allocation for application gateway requires optimization | F18: 73 | K18: 16-30 | L18: 354
A19: Row Labels | B19: Count of Problem Ticket | E19: Resource allocation for Active Directory requires optimization | F19: 71 | K19: 31-60 | L19: 655
A20: Active | B20: 1399 | E20: Resource allocation for disaster recovery requires optimization | F20: 70 | K20: 61-90 | L20: 663
A21: Completed | B21: 601 | E21: Resource allocation for backup verification requires optimization | F21: 70 | K21: Grand Total | L21: 2000
A22: Grand Total | B22: 2000 | E22: Resource allocation for database replication requires optimization | F22: 70
E23: Resource allocation for patch management requires optimization | F23: 68
E24: Resource allocation for configuration management requires optimization | F24: 67
E25: Resource allocation for SAN storage requires optimization | F25: 65
E26: Grand Total | F26: 707
A32: Department Wise Tickets
A33: Row Labels | B33: Count of Problem Ticket
A34: Backup & Recovery | B34: 412
A35: CMDB Team | B35: 478
A36: Database Operations | B36: 428
A37: Infrastructure | B37: 240
A38: Network Operations | B38: 211
A39: Server Management | B39: 231
A40: Grand Total | B40: 2000

Sheet pivot table2
A2: Department, State,Age Buket,Priority Wise Tickets
A3: Count of Problem Ticket | D3: Priority | E3: Status Group | R3: Month | S3: Count of Problem Ticket
D4: Critical | E4: High | F4: Low | G4: Medium | H4: Grand Total | R4: 2025 | S4: 2000
A5: Assigned Team | B5: State | C5: Age Bucket | R5: Q3 | S5: 724
A6: Backup & Recovery | D6: 57 | E6: 108 | F6: 78 | G6: 169 | H6: 412 | R6: 7 | S6: 49
A7: CMDB Team | D7: 70 | E7: 118 | F7: 93 | G7: 197 | H7: 478 | R7: 31 | S7: 49
A8: Database Operations | D8: 74 | E8: 109 | F8: 75 | G8: 170 | H8: 428 | R8: 8 | S8: 675
A9: Infrastructure | D9: 35 | E9: 56 | F9: 62 | G9: 87 | H9: 240 | R9: 31 | S9: 54
A10: Network Operations | D10: 35 | E10: 57 | F10: 42 | G10: 77 | H10: 211 | R10: 32 | S10: 168
A11: Server Management | D11: 30 | E11: 48 | F11: 46 | G11: 107 | H11: 231 | R11: 33 | S11: 152
A12: Grand Total | D12: 301 | E12: 496 | F12: 396 | G12: 807 | H12: 2000 | R12: 34 | S12: 126
R13: 35 | S13: 155 | AC13: Count of Problem Ticket | AD13: Column Labels
R14: 36 | S14: 20 | AC14: Row Labels | AD14: Awaiting Info | AE14: Closed | AF14: In Progress | AG14: Open | AH14: Resolved | AI14: Grand Total
R15: Q4 | S15: 1276 | AC15: Critical | AD15: 34 | AE15: 27 | AF15: 84 | AG15: 95 | AH15: 61 | AI15: 301
R16: 9 | S16: 656 | AC16: High | AD16: 81 | AE16: 46 | AF16: 146 | AG16: 113 | AH16: 110 | AI16: 496
R17: 36 | S17: 136 | AC17: Low | AD17: 62 | AE17: 43 | AF17: 108 | AG17: 110 | AH17: 73 | AI17: 396
R18: 37 | S18: 154 | AC18: Medium | AD18: 134 | AE18: 84 | AF18: 216 | AG18: 216 | AH18: 157 | AI18: 807
R19: 38 | S19: 165 | AC19: Grand Total | AD19: 311 | AE19: 200 | AF19: 554 | AG19: 534 | AH19: 401 | AI19: 2000
R20: 39 | S20: 139
R21: 40 | S21: 62
R22: 10 | S22: 620
R23: 40 | S23: 100
R24: 41 | S24: 160
R25: 42 | S25: 176
R26: 43 | S26: 133
R27: 44 | S27: 51
R28: Grand Total | S28: 2000

Sheet Dashboard
B3: Total Tickets | D3: Active Tickets | F3: Resolution % | H3: Critical Unresolved | J3: Avg Age(days)
B4: ='Calc '!B1 -> 2000 | D4: ='Calc '!B2 -> 1399 | F4: ='Calc '!B3 -> 0.3005 | H4: ='Calc '!B4 -> 213 | J4: ='Calc '!B5 -> 45.498213

Sheet Calc 
A1: Total Tickets | B1: =COUNTA('servicenow data'!A:A)-1 -> 2000
A2: Active Tickets | B2: =COUNTIF('servicenow data'!Y:Y,"Active") -> 1399
A3: Resolution %(active/total) | B3: =1-(B2/B1) -> 0.3005
A4: Critical Unresolved | B4: =COUNTIFS('servicenow data'!F:F,"Critical",'servicenow data'!Y:Y,"Active") -> 213
A5: Avg Age of Active (days) | B5: =AVERAGEIFS('servicenow data'!I:I,'servicenow data'!Y:Y,"Active") -> 45.498213

Sheet Insights 
A1: Finding | B1: Recommendation
A2: About 70% of tickets (1,399 of 2,000) are still active | B2: Review the oldest active tickets and set a target for closing them
A3: 213 of 301 Critical tickets are unresolved | B3: Assign owners and review these daily
A4: CMDB, Database Operations and Backup & Recovery hold about 65% of all tickets | B4: Check whether these teams need more capacity
A5: 311 tickets are Awaiting Info | B5: Follow up on missing information with requesters
A6: Some causes repeat many times (see Top 10 Causes) | B6: Plan permanent fixes for the top causes
